{
    "key":  "p0740",
    "imageKey":  "0740",
    "no":  740,
    "name":  "ケケンカニ",
    "abilities":  [
                      "かいりきバサミ",
                      "てつのこぶし",
                      "いかりのつぼ"
                  ],
    "baseStats":  {
                      "hp":  97,
                      "atk":  132,
                      "def":  77,
                      "spa":  62,
                      "spd":  67,
                      "spe":  43
                  },
    "evioliteEligible":  false,
    "point":  "",
    "synergy":  {
                    "name":  "",
                    "modifiers":  {
                                      "physicalAttacker":  null,
                                      "specialAttacker":  null,
                                      "physicalSweeper":  null,
                                      "specialSweeper":  null,
                                      "physicalWall":  null,
                                      "specialWall":  null,
                                      "setup":  null
                                  }
                },
    "types":  [
                  "かくとう",
                  "こおり"
              ],
    "moves":  [
                  "ギガインパクト",
                  "のしかかり",
                  "からげんき",
                  "がむしゃら",
                  "はかいこうせん",
                  "りんしょう",
                  "いびき",
                  "てだすけ",
                  "ねごと",
                  "いばる",
                  "こらえる",
                  "こわいかお",
                  "まもる",
                  "みがわり",
                  "にほんばれ",
                  "クラブハンマー",
                  "アクアブレイク",
                  "ひやみず",
                  "あまごい",
                  "かみなりパンチ",
                  "いわなだれ",
                  "がんせきふうじ",
                  "ワイドガード",
                  "ダストシュート",
                  "じしん",
                  "あなをほる",
                  "じだんだ",
                  "じならし",
                  "マッドショット",
                  "どろかけ",
                  "アイスハンマー",
                  "アイススピナー",
                  "れいとうパンチ",
                  "ゆきなだれ",
                  "つららばり",
                  "ふぶき",
                  "れいとうビーム",
                  "こごえるかぜ",
                  "ゆきげしき",
                  "きあいパンチ",
                  "インファイト",
                  "ばかぢから",
                  "ばくれつパンチ",
                  "ボディプレス",
                  "ドレインパンチ",
                  "かわらわり",
                  "はやてがえし",
                  "マッハパンチ",
                  "きしかいせい",
                  "きあいだま",
                  "コーチング",
                  "ビルドアップ",
                  "しねんのずつき",
                  "ねむる",
                  "ドわすれ",
                  "はたきおとす",
                  "ぶんまわす",
                  "どろぼう",
                  "しっぺがえし",
                  "なげつける",
                  "アイアンヘッド",
                  "ハードプレス",
                  "てっぺき"
              ]
}
