{
    "key":  "p0730",
    "imageKey":  "0730",
    "no":  730,
    "name":  "アシレーヌ",
    "abilities":  [
                      "げきりゅう",
                      "うるおいボイス"
                  ],
    "baseStats":  {
                      "hp":  80,
                      "atk":  74,
                      "def":  74,
                      "spa":  126,
                      "spd":  116,
                      "spe":  60
                  },
    "evioliteEligible":  false,
    "point":  "",
    "synergy":  {
                    "name":  "",
                    "modifiers":  {
                                      "physicalAttacker":  null,
                                      "specialAttacker":  null,
                                      "physicalSweeper":  null,
                                      "specialSweeper":  null,
                                      "physicalWall":  null,
                                      "specialWall":  null,
                                      "setup":  null
                                  }
                },
    "types":  [
                  "みず",
                  "フェアリー"
              ],
    "moves":  [
                  "ギガインパクト",
                  "のしかかり",
                  "からげんき",
                  "はかいこうせん",
                  "ハイパーボイス",
                  "さわぐ",
                  "りんしょう",
                  "ウェザーボール",
                  "いびき",
                  "てだすけ",
                  "じこあんじ",
                  "アンコール",
                  "ねごと",
                  "メロメロ",
                  "こらえる",
                  "ほろびのうた",
                  "まもる",
                  "みがわり",
                  "うたう",
                  "エナジーボール",
                  "アクアブレイク",
                  "ダイビング",
                  "たきのぼり",
                  "クイックターン",
                  "アクアジェット",
                  "ハイドロカノン",
                  "ハイドロポンプ",
                  "うたかたのアリア",
                  "なみのり",
                  "みずのはどう",
                  "ひやみず",
                  "うずしお",
                  "いのちのしずく",
                  "アクアリング",
                  "あまごい",
                  "アクロバット",
                  "アイススピナー",
                  "トリプルアクセル",
                  "ふぶき",
                  "れいとうビーム",
                  "こごえるかぜ",
                  "ゆきげしき",
                  "くろいきり",
                  "サイコキネシス",
                  "サイコノイズ",
                  "アシストパワー",
                  "ワンダールーム",
                  "めいそう",
                  "ねむる",
                  "ドわすれ",
                  "リフレクター",
                  "ひかりのかべ",
                  "シャドーボール",
                  "アイアンテール",
                  "じゃれつく",
                  "ミストバースト",
                  "ムーンフォース",
                  "みわくのボイス",
                  "マジカルシャイン",
                  "ドレインキッス",
                  "つぶらなひとみ",
                  "ミストフィールド",
                  "あまえる"
              ]
}
