{
    "key":  "p0959",
    "imageKey":  "0959",
    "no":  959,
    "name":  "デカヌチャン",
    "abilities":  [
                      "かたやぶり",
                      "マイペース",
                      "わるいてぐせ"
                  ],
    "baseStats":  {
                      "hp":  85,
                      "atk":  75,
                      "def":  77,
                      "spa":  70,
                      "spd":  105,
                      "spe":  94
                  },
    "evioliteEligible":  false,
    "point":  "",
    "synergy":  {
                    "name":  "",
                    "modifiers":  {
                                      "physicalAttacker":  null,
                                      "specialAttacker":  null,
                                      "physicalSweeper":  null,
                                      "specialSweeper":  null,
                                      "physicalWall":  null,
                                      "specialWall":  null,
                                      "setup":  null
                                  }
                },
    "types":  [
                  "フェアリー",
                  "はがね"
              ],
    "moves":  [
                  "からげんき",
                  "ほしがる",
                  "ねこだまし",
                  "フェイント",
                  "がむしゃら",
                  "てだすけ",
                  "アンコール",
                  "ねごと",
                  "こらえる",
                  "まもる",
                  "みがわり",
                  "いやなおと",
                  "つるぎのまい",
                  "ウッドハンマー",
                  "でんじは",
                  "はいよるいちげき",
                  "とびつく",
                  "ストーンエッジ",
                  "いわなだれ",
                  "がんせきふうじ",
                  "うちおとす",
                  "ステルスロック",
                  "じならし",
                  "アイスハンマー",
                  "かわらわり",
                  "スキルスワップ",
                  "ねむる",
                  "リフレクター",
                  "ひかりのかべ",
                  "イカサマ",
                  "はたきおとす",
                  "ぶんまわす",
                  "どろぼう",
                  "なげつける",
                  "さきおくり",
                  "うそなき",
                  "おだてる",
                  "デカハンマー",
                  "ハードプレス",
                  "ヘビーボンバー",
                  "てっていこうせん",
                  "ラスターカノン",
                  "きんぞくおん",
                  "じゃれつく",
                  "ドレインキッス",
                  "つぶらなひとみ",
                  "てんしのキッス"
              ]
}
