{
    "key":  "p0697",
    "imageKey":  "0697",
    "no":  697,
    "name":  "ガチゴラス",
    "abilities":  [
                      "がんじょうあご",
                      "いしあたま"
                  ],
    "baseStats":  {
                      "hp":  82,
                      "atk":  121,
                      "def":  119,
                      "spa":  69,
                      "spd":  59,
                      "spe":  71
                  },
    "evioliteEligible":  false,
    "point":  "",
    "synergy":  {
                    "name":  "",
                    "modifiers":  {
                                      "physicalAttacker":  null,
                                      "specialAttacker":  null,
                                      "physicalSweeper":  null,
                                      "specialSweeper":  null,
                                      "physicalWall":  null,
                                      "specialWall":  null,
                                      "setup":  null
                                  }
                },
    "types":  [
                  "いわ",
                  "ドラゴン"
              ],
    "moves":  [
                  "ギガインパクト",
                  "あばれる",
                  "のしかかり",
                  "からげんき",
                  "つのドリル",
                  "はかいこうせん",
                  "ハイパーボイス",
                  "りんしょう",
                  "いびき",
                  "ねごと",
                  "メロメロ",
                  "こらえる",
                  "こわいかお",
                  "まもる",
                  "みがわり",
                  "ほえる",
                  "ほのおのキバ",
                  "にほんばれ",
                  "かみなりのキバ",
                  "もろはのずつき",
                  "ストーンエッジ",
                  "いわなだれ",
                  "がんせきふうじ",
                  "ロックブラスト",
                  "メテオビーム",
                  "げんしのちから",
                  "ステルスロック",
                  "ロックカット",
                  "すなあらし",
                  "どくどくのキバ",
                  "じしん",
                  "10まんばりき",
                  "あなをほる",
                  "じだんだ",
                  "じならし",
                  "だいちのちから",
                  "こおりのキバ",
                  "インファイト",
                  "ばかぢから",
                  "かわらわり",
                  "サイコファング",
                  "しねんのずつき",
                  "ねむる",
                  "のろい",
                  "げきりん",
                  "ドラゴンクロー",
                  "ワイドブレイカー",
                  "ドラゴンテール",
                  "スケイルショット",
                  "りゅうせいぐん",
                  "りゅうのはどう",
                  "ドラゴンエール",
                  "りゅうのまい",
                  "かみくだく",
                  "うっぷんばらし",
                  "ぶんまわす",
                  "ダメおし",
                  "かみつく",
                  "あくのはどう",
                  "アイアンテール",
                  "アイアンヘッド",
                  "てっぺき",
                  "じゃれつく",
                  "あまえる"
              ]
}
